textxjinja/__init__.py
textx_jinja-0.4.0.dist-info/licenses/LICENSE
textx_jinja-0.4.0.dist-info/WHEEL
textx_jinja-0.4.0.dist-info/METADATA
textx_jinja-0.4.0.dist-info/RECORD
