Metadata-Version: 2.4
Name: textX-jinja
Version: 0.4.0
Summary: Meta-language for DSL implementation inspired by Xtext
Keywords: textX,generator,template engine,DSL
Author-email: "Igor R. Dejanović" <igor.dejanovic@gmail.com>
Maintainer-email: "Igor R. Dejanović" <igor.dejanovic@gmail.com>
Requires-Python: >=3.8
Classifier: Development Status :: 4 - Beta
Classifier: Intended Audience :: Developers
Classifier: Intended Audience :: Information Technology
Classifier: Intended Audience :: Science/Research
Classifier: Topic :: Software Development :: Interpreters
Classifier: Topic :: Software Development :: Compilers
Classifier: Topic :: Software Development :: Libraries :: Python Modules
Classifier: License :: OSI Approved :: MIT License
Classifier: Operating System :: OS Independent
Classifier: Programming Language :: Python :: 3
Classifier: Programming Language :: Python :: 3.8
Classifier: Programming Language :: Python :: 3.9
Classifier: Programming Language :: Python :: 3.10
Classifier: Programming Language :: Python :: 3.11
Classifier: Programming Language :: Python :: 3.12
Classifier: Programming Language :: Python :: 3.13
License-File: LICENSE
Requires-Dist: textX
Requires-Dist: jinja2
Requires-Dist: ruff ; extra == "dev"
Requires-Dist: flit ; extra == "dev"
Requires-Dist: coverage ; extra == "dev"
Requires-Dist: coveralls ; extra == "dev"
Requires-Dist: pytest ; extra == "dev"
Requires-Dist: ruff ; extra == "test"
Requires-Dist: coverage ; extra == "test"
Requires-Dist: coveralls ; extra == "test"
Requires-Dist: pytest ; extra == "test"
Project-URL: Homepage, https://github.com/textX/textX-jinja/
Project-URL: Repository, https://github.com/textX/textX-jinja/
Provides-Extra: dev
Provides-Extra: test
